<annotation>
	<folder>collectedimages</folder>
	<filename>thumbsup.609e2f07-f6b0-11ec-933b-842afd8851ef.jpg</filename>
	<path>D:\RealTimeObjectDetection\Tensorflow\workspace\images\collectedimages\thumbsup.609e2f07-f6b0-11ec-933b-842afd8851ef.jpg</path>
	<source>
		<database>Unknown</database>
	</source>
	<size>
		<width>640</width>
		<height>480</height>
		<depth>3</depth>
	</size>
	<segmented>0</segmented>
	<object>
		<name>thumbsup</name>
		<pose>Unspecified</pose>
		<truncated>1</truncated>
		<difficult>0</difficult>
		<bndbox>
			<xmin>518</xmin>
			<ymin>159</ymin>
			<xmax>640</xmax>
			<ymax>357</ymax>
		</bndbox>
	</object>
</annotation>
