<annotation>
	<folder>yes</folder>
	<filename>yes.580d08fd-f7a3-11ec-8d18-1cbfc0a47a93.jpg</filename>
	<path>D:\RealTimeObjectDetection\Tensorflow\workspace\images\collectedimages\yes\yes.580d08fd-f7a3-11ec-8d18-1cbfc0a47a93.jpg</path>
	<source>
		<database>Unknown</database>
	</source>
	<size>
		<width>640</width>
		<height>480</height>
		<depth>3</depth>
	</size>
	<segmented>0</segmented>
	<object>
		<name>yes</name>
		<pose>Unspecified</pose>
		<truncated>0</truncated>
		<difficult>0</difficult>
		<bndbox>
			<xmin>62</xmin>
			<ymin>236</ymin>
			<xmax>268</xmax>
			<ymax>401</ymax>
		</bndbox>
	</object>
</annotation>
