<annotation>
	<folder>collectedimages</folder>
	<filename>yes.597cc9d3-f6ae-11ec-8fed-842afd8851ef.jpg</filename>
	<path>D:\RealTimeObjectDetection\Tensorflow\workspace\images\collectedimages\yes.597cc9d3-f6ae-11ec-8fed-842afd8851ef.jpg</path>
	<source>
		<database>Unknown</database>
	</source>
	<size>
		<width>640</width>
		<height>480</height>
		<depth>3</depth>
	</size>
	<segmented>0</segmented>
	<object>
		<name>yes</name>
		<pose>Unspecified</pose>
		<truncated>0</truncated>
		<difficult>0</difficult>
		<bndbox>
			<xmin>54</xmin>
			<ymin>226</ymin>
			<xmax>203</xmax>
			<ymax>333</ymax>
		</bndbox>
	</object>
</annotation>
